searchfox/__init__.py
searchfox/searchfox.cpython-312-x86_64-linux-gnu.so
searchfox_py-0.8.0.dist-info/METADATA
searchfox_py-0.8.0.dist-info/WHEEL
searchfox_py-0.8.0.dist-info/RECORD
