Metadata-Version: 2.4
Name: searchfox-py
Version: 0.8.0
Summary: Python bindings for searchfox.org API
License: MIT OR Apache-2.0
